LICENSE
MANIFEST.in
README.md
requirements.txt
setup.py
frangidoc/__init__.py
frangidoc/__main__.py
frangidoc/api.py
frangidoc/discover.py
frangidoc/objects.py
frangidoc/parser.py
frangidoc/renderer.py
frangidoc.egg-info/PKG-INFO
frangidoc.egg-info/SOURCES.txt
frangidoc.egg-info/dependency_links.txt
frangidoc.egg-info/requires.txt
frangidoc.egg-info/top_level.txt