Metadata-Version: 1.1
Name: frangidoc
Version: 2.1.3
Summary: Generate markdown from Python sources (reST based)
Home-page: https://github.com/MrFrangipane/frangidoc
Author: Valentin Moriceau
Author-email: valentin.moriceau@free.com
License: UNKNOWN
Keywords: documentation markdown docstring reST
Platform: UNKNOWN
Classifier: Development Status :: 3 - Alpha
Classifier: Programming Language :: Python :: 2.7
Classifier: Programming Language :: Python :: 3
Classifier: Intended Audience :: Developers
Classifier: Intended Audience :: System Administrators
Classifier: License :: OSI Approved :: GNU General Public License v3 (GPLv3)
Classifier: Topic :: Software Development :: Documentation
Classifier: Operating System :: Microsoft
Classifier: Operating System :: POSIX
